{
    "meta": {
        "name": "Wallet Collection",
        "addedAt": 1768933629,
        "type": "wallet"
    },
    "policy": {
        "policyId": "c136a71a17ce49b66a7eb5c90aa20d0563bf66ef9928351e19419cda"
    },
    "assets_cache": [
        {
            "asset": "c136a71a17ce49b66a7eb5c90aa20d0563bf66ef9928351e19419cda4265796f6e64436974697a656e3030383033",
            "quantity": null,
            "policy_id": "c136a71a17ce49b66a7eb5c90aa20d0563bf66ef9928351e19419cda",
            "asset_name": "4265796f6e64436974697a656e3030383033",
            "onchain_metadata": {
                "dna": "Zombie",
                "eyes": "Sunglasses",
                "hair": "Widow's Peak White",
                "name": "Beyond Citizen #00803",
                "files": [
                    {
                        "src": "ipfs:\/\/QmQphWGqyTwT1gBkkKKQNa5ARQCxBCJhvDRXnhkGF4zPNp",
                        "name": "Beyond Citizen #00803",
                        "mediaType": "image\/jpeg"
                    },
                    {
                        "src": "ipfs:\/\/QmQrqqM4ryfEDgS3x7GZrxQG1erk3nNd2LLE3SKwc6XDPj",
                        "name": "Beyond Citizens Passport",
                        "mediaType": "video\/mp4"
                    }
                ],
                "image": "ipfs:\/\/QmQphWGqyTwT1gBkkKKQNa5ARQCxBCJhvDRXnhkGF4zPNp",
                "mouth": "Tongue Out",
                "clothes": "School Uniform",
                "earring": "None",
                "eyebrow": "Angry",
                "headwear": "Sideways Propeller Hat",
                "mediaType": "image\/jpeg",
                "Collection": "Beyond Citizens by Beyond Rockets",
                "background": "Crimson Red"
            }
        },
        {
            "asset": "c136a71a17ce49b66a7eb5c90aa20d0563bf66ef9928351e19419cda4265796f6e64436974697a656e3033343133",
            "quantity": null,
            "policy_id": "c136a71a17ce49b66a7eb5c90aa20d0563bf66ef9928351e19419cda",
            "asset_name": "4265796f6e64436974697a656e3033343133",
            "onchain_metadata": {
                "dna": "Human",
                "eyes": "Heterochromia",
                "hair": "Bowls Brown",
                "name": "Beyond Citizen #03413",
                "files": [
                    {
                        "src": "ipfs:\/\/QmQAFAWwqBWZBiRmN7wDFG12ZDnXRXpZ95fzzwMp42gYVh",
                        "name": "Beyond Citizen #03413",
                        "mediaType": "image\/jpeg"
                    },
                    {
                        "src": "ipfs:\/\/QmQrqqM4ryfEDgS3x7GZrxQG1erk3nNd2LLE3SKwc6XDPj",
                        "name": "Beyond Citizens Passport",
                        "mediaType": "video\/mp4"
                    }
                ],
                "image": "ipfs:\/\/QmQAFAWwqBWZBiRmN7wDFG12ZDnXRXpZ95fzzwMp42gYVh",
                "mouth": "Tongue Out",
                "clothes": "Rockstar Tank Top",
                "earring": "Titanium Earrings",
                "eyebrow": "Thick",
                "headwear": "None",
                "mediaType": "image\/jpeg",
                "Collection": "Beyond Citizens by Beyond Rockets",
                "background": "Crimson Red"
            }
        },
        {
            "asset": "c136a71a17ce49b66a7eb5c90aa20d0563bf66ef9928351e19419cda4265796f6e64436974697a656e3036323932",
            "quantity": null,
            "policy_id": "c136a71a17ce49b66a7eb5c90aa20d0563bf66ef9928351e19419cda",
            "asset_name": "4265796f6e64436974697a656e3036323932",
            "onchain_metadata": {
                "dna": "Human",
                "eyes": "Visor",
                "hair": "Pixie Cut Blue",
                "name": "Beyond Citizen #06292",
                "files": [
                    {
                        "src": "ipfs:\/\/QmWX4ivdB3JLNrVz6dReHc95RYDeEVdEuyFcqSsBtGEp1z",
                        "name": "Beyond Citizen #06292",
                        "mediaType": "image\/jpeg"
                    },
                    {
                        "src": "ipfs:\/\/QmQrqqM4ryfEDgS3x7GZrxQG1erk3nNd2LLE3SKwc6XDPj",
                        "name": "Beyond Citizens Passport",
                        "mediaType": "video\/mp4"
                    }
                ],
                "image": "ipfs:\/\/QmWX4ivdB3JLNrVz6dReHc95RYDeEVdEuyFcqSsBtGEp1z",
                "mouth": "Grin",
                "clothes": "Icon Hoodie White",
                "earring": "Gold Piercings",
                "eyebrow": "Slit",
                "headwear": "None",
                "mediaType": "image\/jpeg",
                "Collection": "Beyond Citizens by Beyond Rockets",
                "background": "Mustard Yellow"
            }
        }
    ]
}